cppumap/LICENSE
cppumap/README.MD
cppumap/__init__.py
cppumap/cppum.pyx
cppumap/cppum_compile.py
cppumap/joinall.py
cppumap/requirements.txt
cppumap/thirdparty.json
cppumap-0.10.dist-info/LICENSE.rst
cppumap-0.10.dist-info/METADATA
cppumap-0.10.dist-info/WHEEL
cppumap-0.10.dist-info/top_level.txt
cppumap-0.10.dist-info/RECORD
