Metadata-Version: 2.1
Name: cppumap
Version: 0.10
Summary: C++ unordered map for Python
Home-page: https://github.com/hansalemaos/cppumap
Author: Johannes Fischer
Author-email: aulasparticularesdealemaosp@gmail.com
License: MIT
Keywords: c++,map
Classifier: Development Status :: 4 - Beta
Classifier: Programming Language :: Python :: 3 :: Only
Classifier: Programming Language :: Python :: 3.10
Classifier: Topic :: Software Development :: Libraries :: Python Modules
Classifier: Topic :: Utilities
License-File: LICENSE.rst
Requires-Dist: Cython
Requires-Dist: list-all-files-recursively
Requires-Dist: numpy
Requires-Dist: setuptools
